{
  "id": "popular_brands",
  "label": "Popular Brands",
  "format": "custom",
  "repeatable": true,
  "status": true,
  "json": {
    "Main": {
      "uid": {
        "config": {
          "label": "UID"
        },
        "type": "UID"
      },
      "brand": {
        "type": "Group",
        "config": {
          "label": "Brand",
          "fields": {
            "title": {
              "type": "Text",
              "config": {
                "label": "Title",
                "placeholder": ""
              }
            },
            "logo": {
              "type": "Image",
              "config": {
                "label": "Logo",
                "constraint": {},
                "thumbnails": []
              }
            }
          }
        }
      }
    }
  }
}
